QrCode/__init__.py
QrCode/admin.py
QrCode/apps.py
QrCode/models.py
QrCode/tests.py
QrCode/urls.py
QrCode/views.py
taggenerator-1.0.2.dist-info/LICENSE
taggenerator-1.0.2.dist-info/METADATA
taggenerator-1.0.2.dist-info/WHEEL
taggenerator-1.0.2.dist-info/top_level.txt
taggenerator-1.0.2.dist-info/RECORD
