Metadata-Version: 2.2
Name: TagGenerator
Version: 1.0.2
Summary: A reusable Django app for QR Code generation
Home-page: https://github.com/DadaNanjesha/TagGenerator
Author: Dada Nanjesha
Classifier: Framework :: Django
Classifier: Programming Language :: Python :: 3
Classifier: License :: OSI Approved :: MIT License
Classifier: Operating System :: OS Independent
Requires-Python: >=3.9
License-File: LICENSE
Requires-Dist: Django>=4.0
Requires-Dist: qrcode
Requires-Dist: Pillow
Dynamic: author
Dynamic: classifier
Dynamic: description
Dynamic: description-content-type
Dynamic: home-page
Dynamic: requires-dist
Dynamic: requires-python
Dynamic: summary
